odoo8_addon_l10n_fr_chorus_sale_stock-8.0.1.0.0.99.dev2-py2.7-nspkg.pth
odoo8_addon_l10n_fr_chorus_sale_stock-8.0.1.0.0.99.dev2.dist-info/METADATA
odoo8_addon_l10n_fr_chorus_sale_stock-8.0.1.0.0.99.dev2.dist-info/RECORD
odoo8_addon_l10n_fr_chorus_sale_stock-8.0.1.0.0.99.dev2.dist-info/WHEEL
odoo8_addon_l10n_fr_chorus_sale_stock-8.0.1.0.0.99.dev2.dist-info/namespace_packages.txt
odoo8_addon_l10n_fr_chorus_sale_stock-8.0.1.0.0.99.dev2.dist-info/top_level.txt
odoo_addons/l10n_fr_chorus_sale_stock/README.rst
odoo_addons/l10n_fr_chorus_sale_stock/__init__.py
odoo_addons/l10n_fr_chorus_sale_stock/__openerp__.py
odoo_addons/l10n_fr_chorus_sale_stock/i18n/l10n_fr_chorus_sale_stock.pot
odoo_addons/l10n_fr_chorus_sale_stock/models/__init__.py
odoo_addons/l10n_fr_chorus_sale_stock/models/stock_picking.py
odoo_addons/l10n_fr_chorus_sale_stock/static/description/icon.png
