Metadata-Version: 2.1
Name: odoo8-addon-l10n-fr-chorus-sale-stock
Version: 8.0.1.0.0.99.dev2
Summary: Copy public market from sale order to invoice
Home-page: http://www.akretion.com
Author: Akretion,Odoo Community Association (OCA)
Author-email: support@odoo-community.org
License: AGPL-3
Platform: UNKNOWN
Classifier: Programming Language :: Python
Classifier: Framework :: Odoo
Classifier: License :: OSI Approved :: GNU Affero General Public License v3
Requires-Python: ~=2.7
Requires-Dist: odoo8-addon-l10n-fr-chorus-sale
Requires-Dist: odoo (<9.0a,>=8.0a)
